cachewrapper/__init__.py
cachewrapper/core.py
cachewrapper/release.py
cachewrapper/utils.py
cachewrapper-0.1.1.dist-info/licenses/LICENSE
cachewrapper-0.1.1.dist-info/METADATA
cachewrapper-0.1.1.dist-info/WHEEL
cachewrapper-0.1.1.dist-info/top_level.txt
cachewrapper-0.1.1.dist-info/RECORD
