Metadata-Version: 2.4
Name: cachewrapper
Version: 0.1.1
Summary: thin layer to facilitate caching of api calls
Home-page: https://codeberg.org/cark/cachewrapper
Author: Carsten Knoll
Author-email: firstname.lastname@posteo.de
License: GPLv3
Classifier: Development Status :: 3 - Alpha
Classifier: Intended Audience :: Developers
Classifier: License :: OSI Approved :: GNU General Public License v3 (GPLv3)
Classifier: Programming Language :: Python :: 3
License-File: LICENSE
Dynamic: author
Dynamic: author-email
Dynamic: classifier
Dynamic: description
Dynamic: home-page
Dynamic: license
Dynamic: license-file
Dynamic: summary
